<?xml version="1.0" encoding="UTF-8"?>
<sem:triples uri="http://www.lds.org/vrl/specific-people/media" xmlns:sem="http://marklogic.com/semantics">
  <sem:triple>
    <sem:subject>http://www.lds.org/vrl/specific-people/media</sem:subject>
    <sem:predicate>http://www.w3.org/2004/02/skos/core#prefLabel</sem:predicate>
    <sem:object datatype="xsd:string" xml:lang="eng">MEDIA</sem:object>
  </sem:triple>
  <sem:triple>
    <sem:subject>http://www.lds.org/vrl/specific-people/media</sem:subject>
    <sem:predicate>http://www.w3.org/2004/02/skos/core#inScheme</sem:predicate>
    <sem:object datatype="sem:iri">http://www.lds.org/concept-scheme/vrl</sem:object>
  </sem:triple>
  <sem:triple>
    <sem:subject>http://www.lds.org/vrl/specific-people/media</sem:subject>
    <sem:predicate>http://www.lds.org/core#entityType</sem:predicate>
    <sem:object datatype="sem:iri">http://www.schema.org/Place</sem:object>
  </sem:triple>
  <sem:triple>
    <sem:subject>http://www.lds.org/vrl/specific-people/media</sem:subject>
    <sem:predicate>http://www.w3.org/2004/02/skos/core#broader</sem:predicate>
    <sem:object datatype="sem:iri">http://www.lds.org/vrl/specific-people/media/adamson-zachary</sem:object>
  </sem:triple>
  <sem:triple>
    <sem:subject>http://www.lds.org/vrl/specific-people/media</sem:subject>
    <sem:predicate>http://www.w3.org/2004/02/skos/core#broader</sem:predicate>
    <sem:object datatype="sem:iri">http://www.lds.org/vrl/specific-people/media/allred-carol-ann</sem:object>
  </sem:triple>
  <sem:triple>
    <sem:subject>http://www.lds.org/vrl/specific-people/media</sem:subject>
    <sem:predicate>http://www.w3.org/2004/02/skos/core#broader</sem:predicate>
    <sem:object datatype="sem:iri">http://www.lds.org/vrl/specific-people/media/anderson-barry</sem:object>
  </sem:triple>
  <sem:triple>
    <sem:subject>http://www.lds.org/vrl/specific-people/media</sem:subject>
    <sem:predicate>http://www.w3.org/2004/02/skos/core#broader</sem:predicate>
    <sem:object datatype="sem:iri">http://www.lds.org/vrl/specific-people/media/anderson-jimmy</sem:object>
  </sem:triple>
  <sem:triple>
    <sem:subject>http://www.lds.org/vrl/specific-people/media</sem:subject>
    <sem:predicate>http://www.w3.org/2004/02/skos/core#broader</sem:predicate>
    <sem:object datatype="sem:iri">http://www.lds.org/vrl/specific-people/media/archuleta-david</sem:object>
  </sem:triple>
  <sem:triple>
    <sem:subject>http://www.lds.org/vrl/specific-people/media</sem:subject>
    <sem:predicate>http://www.w3.org/2004/02/skos/core#broader</sem:predicate>
    <sem:object datatype="sem:iri">http://www.lds.org/vrl/specific-people/media/asper-frank-wilson-1892-1973</sem:object>
  </sem:triple>
  <sem:triple>
    <sem:subject>http://www.lds.org/vrl/specific-people/media</sem:subject>
    <sem:predicate>http://www.w3.org/2004/02/skos/core#broader</sem:predicate>
    <sem:object datatype="sem:iri">http://www.lds.org/vrl/specific-people/media/babidge-darrell</sem:object>
  </sem:triple>
  <sem:triple>
    <sem:subject>http://www.lds.org/vrl/specific-people/media</sem:subject>
    <sem:predicate>http://www.w3.org/2004/02/skos/core#broader</sem:predicate>
    <sem:object datatype="sem:iri">http://www.lds.org/vrl/specific-people/media/babidge-welch</sem:object>
  </sem:triple>
  <sem:triple>
    <sem:subject>http://www.lds.org/vrl/specific-people/media</sem:subject>
    <sem:predicate>http://www.w3.org/2004/02/skos/core#broader</sem:predicate>
    <sem:object datatype="sem:iri">http://www.lds.org/vrl/specific-people/media/bach-johann-sebastian</sem:object>
  </sem:triple>
  <sem:triple>
    <sem:subject>http://www.lds.org/vrl/specific-people/media</sem:subject>
    <sem:predicate>http://www.w3.org/2004/02/skos/core#broader</sem:predicate>
    <sem:object datatype="sem:iri">http://www.lds.org/vrl/specific-people/media/baker-jenny-oaks</sem:object>
  </sem:triple>
  <sem:triple>
    <sem:subject>http://www.lds.org/vrl/specific-people/media</sem:subject>
    <sem:predicate>http://www.w3.org/2004/02/skos/core#broader</sem:predicate>
    <sem:object datatype="sem:iri">http://www.lds.org/vrl/specific-people/media/ballam-michael</sem:object>
  </sem:triple>
  <sem:triple>
    <sem:subject>http://www.lds.org/vrl/specific-people/media</sem:subject>
    <sem:predicate>http://www.w3.org/2004/02/skos/core#broader</sem:predicate>
    <sem:object datatype="sem:iri">http://www.lds.org/vrl/specific-people/media/ballantyne-wendell</sem:object>
  </sem:triple>
  <sem:triple>
    <sem:subject>http://www.lds.org/vrl/specific-people/media</sem:subject>
    <sem:predicate>http://www.w3.org/2004/02/skos/core#broader</sem:predicate>
    <sem:object datatype="sem:iri">http://www.lds.org/vrl/specific-people/media/bayles-dallyn-vail</sem:object>
  </sem:triple>
  <sem:triple>
    <sem:subject>http://www.lds.org/vrl/specific-people/media</sem:subject>
    <sem:predicate>http://www.w3.org/2004/02/skos/core#broader</sem:predicate>
    <sem:object datatype="sem:iri">http://www.lds.org/vrl/specific-people/media/beethoven</sem:object>
  </sem:triple>
  <sem:triple>
    <sem:subject>http://www.lds.org/vrl/specific-people/media</sem:subject>
    <sem:predicate>http://www.w3.org/2004/02/skos/core#broader</sem:predicate>
    <sem:object datatype="sem:iri">http://www.lds.org/vrl/specific-people/media/beetles</sem:object>
  </sem:triple>
  <sem:triple>
    <sem:subject>http://www.lds.org/vrl/specific-people/media</sem:subject>
    <sem:predicate>http://www.w3.org/2004/02/skos/core#broader</sem:predicate>
    <sem:object datatype="sem:iri">http://www.lds.org/vrl/specific-people/media/bestor-kurt</sem:object>
  </sem:triple>
  <sem:triple>
    <sem:subject>http://www.lds.org/vrl/specific-people/media</sem:subject>
    <sem:predicate>http://www.w3.org/2004/02/skos/core#broader</sem:predicate>
    <sem:object datatype="sem:iri">http://www.lds.org/vrl/specific-people/media/bevan-julie</sem:object>
  </sem:triple>
  <sem:triple>
    <sem:subject>http://www.lds.org/vrl/specific-people/media</sem:subject>
    <sem:predicate>http://www.w3.org/2004/02/skos/core#broader</sem:predicate>
    <sem:object datatype="sem:iri">http://www.lds.org/vrl/specific-people/media/bloom-claire</sem:object>
  </sem:triple>
  <sem:triple>
    <sem:subject>http://www.lds.org/vrl/specific-people/media</sem:subject>
    <sem:predicate>http://www.w3.org/2004/02/skos/core#broader</sem:predicate>
    <sem:object datatype="sem:iri">http://www.lds.org/vrl/specific-people/media/bocelli-andrea</sem:object>
  </sem:triple>
  <sem:triple>
    <sem:subject>http://www.lds.org/vrl/specific-people/media</sem:subject>
    <sem:predicate>http://www.w3.org/2004/02/skos/core#broader</sem:predicate>
    <sem:object datatype="sem:iri">http://www.lds.org/vrl/specific-people/media/bowden-robert-c</sem:object>
  </sem:triple>
  <sem:triple>
    <sem:subject>http://www.lds.org/vrl/specific-people/media</sem:subject>
    <sem:predicate>http://www.w3.org/2004/02/skos/core#broader</sem:predicate>
    <sem:object datatype="sem:iri">http://www.lds.org/vrl/specific-people/media/bradford-daron</sem:object>
  </sem:triple>
  <sem:triple>
    <sem:subject>http://www.lds.org/vrl/specific-people/media</sem:subject>
    <sem:predicate>http://www.w3.org/2004/02/skos/core#broader</sem:predicate>
    <sem:object datatype="sem:iri">http://www.lds.org/vrl/specific-people/media/bradshaw-merrill</sem:object>
  </sem:triple>
  <sem:triple>
    <sem:subject>http://www.lds.org/vrl/specific-people/media</sem:subject>
    <sem:predicate>http://www.w3.org/2004/02/skos/core#broader</sem:predicate>
    <sem:object datatype="sem:iri">http://www.lds.org/vrl/specific-people/media/brainerd-clayton</sem:object>
  </sem:triple>
  <sem:triple>
    <sem:subject>http://www.lds.org/vrl/specific-people/media</sem:subject>
    <sem:predicate>http://www.w3.org/2004/02/skos/core#broader</sem:predicate>
    <sem:object datatype="sem:iri">http://www.lds.org/vrl/specific-people/media/braithewaite-anna-mooy</sem:object>
  </sem:triple>
  <sem:triple>
    <sem:subject>http://www.lds.org/vrl/specific-people/media</sem:subject>
    <sem:predicate>http://www.w3.org/2004/02/skos/core#broader</sem:predicate>
    <sem:object datatype="sem:iri">http://www.lds.org/vrl/specific-people/media/breault-robert</sem:object>
  </sem:triple>
  <sem:triple>
    <sem:subject>http://www.lds.org/vrl/specific-people/media</sem:subject>
    <sem:predicate>http://www.w3.org/2004/02/skos/core#broader</sem:predicate>
    <sem:object datatype="sem:iri">http://www.lds.org/vrl/specific-people/media/bybee-ariel</sem:object>
  </sem:triple>
  <sem:triple>
    <sem:subject>http://www.lds.org/vrl/specific-people/media</sem:subject>
    <sem:predicate>http://www.w3.org/2004/02/skos/core#broader</sem:predicate>
    <sem:object datatype="sem:iri">http://www.lds.org/vrl/specific-people/media/call-cherie</sem:object>
  </sem:triple>
  <sem:triple>
    <sem:subject>http://www.lds.org/vrl/specific-people/media</sem:subject>
    <sem:predicate>http://www.w3.org/2004/02/skos/core#broader</sem:predicate>
    <sem:object datatype="sem:iri">http://www.lds.org/vrl/specific-people/media/campbell-meredith</sem:object>
  </sem:triple>
  <sem:triple>
    <sem:subject>http://www.lds.org/vrl/specific-people/media</sem:subject>
    <sem:predicate>http://www.w3.org/2004/02/skos/core#broader</sem:predicate>
    <sem:object datatype="sem:iri">http://www.lds.org/vrl/specific-people/media/careless-george</sem:object>
  </sem:triple>
  <sem:triple>
    <sem:subject>http://www.lds.org/vrl/specific-people/media</sem:subject>
    <sem:predicate>http://www.w3.org/2004/02/skos/core#broader</sem:predicate>
    <sem:object datatype="sem:iri">http://www.lds.org/vrl/specific-people/media/careless-george-edward-percy-1839-1932</sem:object>
  </sem:triple>
  <sem:triple>
    <sem:subject>http://www.lds.org/vrl/specific-people/media</sem:subject>
    <sem:predicate>http://www.w3.org/2004/02/skos/core#broader</sem:predicate>
    <sem:object datatype="sem:iri">http://www.lds.org/vrl/specific-people/media/carter-dan</sem:object>
  </sem:triple>
  <sem:triple>
    <sem:subject>http://www.lds.org/vrl/specific-people/media</sem:subject>
    <sem:predicate>http://www.w3.org/2004/02/skos/core#broader</sem:predicate>
    <sem:object datatype="sem:iri">http://www.lds.org/vrl/specific-people/media/chase-isaac</sem:object>
  </sem:triple>
  <sem:triple>
    <sem:subject>http://www.lds.org/vrl/specific-people/media</sem:subject>
    <sem:predicate>http://www.w3.org/2004/02/skos/core#broader</sem:predicate>
    <sem:object datatype="sem:iri">http://www.lds.org/vrl/specific-people/media/chipman-michael</sem:object>
  </sem:triple>
  <sem:triple>
    <sem:subject>http://www.lds.org/vrl/specific-people/media</sem:subject>
    <sem:predicate>http://www.w3.org/2004/02/skos/core#broader</sem:predicate>
    <sem:object datatype="sem:iri">http://www.lds.org/vrl/specific-people/media/chopin-frederic</sem:object>
  </sem:triple>
  <sem:triple>
    <sem:subject>http://www.lds.org/vrl/specific-people/media</sem:subject>
    <sem:predicate>http://www.w3.org/2004/02/skos/core#broader</sem:predicate>
    <sem:object datatype="sem:iri">http://www.lds.org/vrl/specific-people/media/christensen-mac</sem:object>
  </sem:triple>
  <sem:triple>
    <sem:subject>http://www.lds.org/vrl/specific-people/media</sem:subject>
    <sem:predicate>http://www.w3.org/2004/02/skos/core#broader</sem:predicate>
    <sem:object datatype="sem:iri">http://www.lds.org/vrl/specific-people/media/christiansen-clay</sem:object>
  </sem:triple>
  <sem:triple>
    <sem:subject>http://www.lds.org/vrl/specific-people/media</sem:subject>
    <sem:predicate>http://www.w3.org/2004/02/skos/core#broader</sem:predicate>
    <sem:object datatype="sem:iri">http://www.lds.org/vrl/specific-people/media/clark-brian-neal</sem:object>
  </sem:triple>
  <sem:triple>
    <sem:subject>http://www.lds.org/vrl/specific-people/media</sem:subject>
    <sem:predicate>http://www.w3.org/2004/02/skos/core#broader</sem:predicate>
    <sem:object datatype="sem:iri">http://www.lds.org/vrl/specific-people/media/clawson-hiram-bradley-1826-1912</sem:object>
  </sem:triple>
  <sem:triple>
    <sem:subject>http://www.lds.org/vrl/specific-people/media</sem:subject>
    <sem:predicate>http://www.w3.org/2004/02/skos/core#broader</sem:predicate>
    <sem:object datatype="sem:iri">http://www.lds.org/vrl/specific-people/media/clayton-william</sem:object>
  </sem:triple>
  <sem:triple>
    <sem:subject>http://www.lds.org/vrl/specific-people/media</sem:subject>
    <sem:predicate>http://www.w3.org/2004/02/skos/core#broader</sem:predicate>
    <sem:object datatype="sem:iri">http://www.lds.org/vrl/specific-people/media/cleobury-stephen</sem:object>
  </sem:triple>
  <sem:triple>
    <sem:subject>http://www.lds.org/vrl/specific-people/media</sem:subject>
    <sem:predicate>http://www.w3.org/2004/02/skos/core#broader</sem:predicate>
    <sem:object datatype="sem:iri">http://www.lds.org/vrl/specific-people/media/cock-christopher</sem:object>
  </sem:triple>
  <sem:triple>
    <sem:subject>http://www.lds.org/vrl/specific-people/media</sem:subject>
    <sem:predicate>http://www.w3.org/2004/02/skos/core#broader</sem:predicate>
    <sem:object datatype="sem:iri">http://www.lds.org/vrl/specific-people/media/cole-natalie</sem:object>
  </sem:triple>
  <sem:triple>
    <sem:subject>http://www.lds.org/vrl/specific-people/media</sem:subject>
    <sem:predicate>http://www.w3.org/2004/02/skos/core#broader</sem:predicate>
    <sem:object datatype="sem:iri">http://www.lds.org/vrl/specific-people/media/condie-richard-p</sem:object>
  </sem:triple>
  <sem:triple>
    <sem:subject>http://www.lds.org/vrl/specific-people/media</sem:subject>
    <sem:predicate>http://www.w3.org/2004/02/skos/core#broader</sem:predicate>
    <sem:object datatype="sem:iri">http://www.lds.org/vrl/specific-people/media/cope-kenneth</sem:object>
  </sem:triple>
  <sem:triple>
    <sem:subject>http://www.lds.org/vrl/specific-people/media</sem:subject>
    <sem:predicate>http://www.w3.org/2004/02/skos/core#broader</sem:predicate>
    <sem:object datatype="sem:iri">http://www.lds.org/vrl/specific-people/media/cornwall-j-spencer</sem:object>
  </sem:triple>
  <sem:triple>
    <sem:subject>http://www.lds.org/vrl/specific-people/media</sem:subject>
    <sem:predicate>http://www.w3.org/2004/02/skos/core#broader</sem:predicate>
    <sem:object datatype="sem:iri">http://www.lds.org/vrl/specific-people/media/cowan-ken</sem:object>
  </sem:triple>
  <sem:triple>
    <sem:subject>http://www.lds.org/vrl/specific-people/media</sem:subject>
    <sem:predicate>http://www.w3.org/2004/02/skos/core#broader</sem:predicate>
    <sem:object datatype="sem:iri">http://www.lds.org/vrl/specific-people/media/cronkite-walter</sem:object>
  </sem:triple>
  <sem:triple>
    <sem:subject>http://www.lds.org/vrl/specific-people/media</sem:subject>
    <sem:predicate>http://www.w3.org/2004/02/skos/core#broader</sem:predicate>
    <sem:object datatype="sem:iri">http://www.lds.org/vrl/specific-people/media/cundick-robert</sem:object>
  </sem:triple>
  <sem:triple>
    <sem:subject>http://www.lds.org/vrl/specific-people/media</sem:subject>
    <sem:predicate>http://www.w3.org/2004/02/skos/core#broader</sem:predicate>
    <sem:object datatype="sem:iri">http://www.lds.org/vrl/specific-people/media/dan-george-chief</sem:object>
  </sem:triple>
  <sem:triple>
    <sem:subject>http://www.lds.org/vrl/specific-people/media</sem:subject>
    <sem:predicate>http://www.w3.org/2004/02/skos/core#broader</sem:predicate>
    <sem:object datatype="sem:iri">http://www.lds.org/vrl/specific-people/media/darley-roy-m</sem:object>
  </sem:triple>
  <sem:triple>
    <sem:subject>http://www.lds.org/vrl/specific-people/media</sem:subject>
    <sem:predicate>http://www.w3.org/2004/02/skos/core#broader</sem:predicate>
    <sem:object datatype="sem:iri">http://www.lds.org/vrl/specific-people/media/darley-roy-maughan-1918-2003</sem:object>
  </sem:triple>
  <sem:triple>
    <sem:subject>http://www.lds.org/vrl/specific-people/media</sem:subject>
    <sem:predicate>http://www.w3.org/2004/02/skos/core#broader</sem:predicate>
    <sem:object datatype="sem:iri">http://www.lds.org/vrl/specific-people/media/daynes-joseph-j</sem:object>
  </sem:triple>
  <sem:triple>
    <sem:subject>http://www.lds.org/vrl/specific-people/media</sem:subject>
    <sem:predicate>http://www.w3.org/2004/02/skos/core#broader</sem:predicate>
    <sem:object datatype="sem:iri">http://www.lds.org/vrl/specific-people/media/daynes-joseph-john-1851-1920</sem:object>
  </sem:triple>
  <sem:triple>
    <sem:subject>http://www.lds.org/vrl/specific-people/media</sem:subject>
    <sem:predicate>http://www.w3.org/2004/02/skos/core#broader</sem:predicate>
    <sem:object datatype="sem:iri">http://www.lds.org/vrl/specific-people/media/deadrick-gail</sem:object>
  </sem:triple>
  <sem:triple>
    <sem:subject>http://www.lds.org/vrl/specific-people/media</sem:subject>
    <sem:predicate>http://www.w3.org/2004/02/skos/core#broader</sem:predicate>
    <sem:object datatype="sem:iri">http://www.lds.org/vrl/specific-people/media/deford-sally</sem:object>
  </sem:triple>
  <sem:triple>
    <sem:subject>http://www.lds.org/vrl/specific-people/media</sem:subject>
    <sem:predicate>http://www.w3.org/2004/02/skos/core#broader</sem:predicate>
    <sem:object datatype="sem:iri">http://www.lds.org/vrl/specific-people/media/domiciano-liriel</sem:object>
  </sem:triple>
  <sem:triple>
    <sem:subject>http://www.lds.org/vrl/specific-people/media</sem:subject>
    <sem:predicate>http://www.w3.org/2004/02/skos/core#broader</sem:predicate>
    <sem:object datatype="sem:iri">http://www.lds.org/vrl/specific-people/media/duehlmeier-susan</sem:object>
  </sem:triple>
  <sem:triple>
    <sem:subject>http://www.lds.org/vrl/specific-people/media</sem:subject>
    <sem:predicate>http://www.w3.org/2004/02/skos/core#broader</sem:predicate>
    <sem:object datatype="sem:iri">http://www.lds.org/vrl/specific-people/media/duffy-kiera</sem:object>
  </sem:triple>
  <sem:triple>
    <sem:subject>http://www.lds.org/vrl/specific-people/media</sem:subject>
    <sem:predicate>http://www.w3.org/2004/02/skos/core#broader</sem:predicate>
    <sem:object datatype="sem:iri">http://www.lds.org/vrl/specific-people/media/duncan-wi</sem:object>
  </sem:triple>
  <sem:triple>
    <sem:subject>http://www.lds.org/vrl/specific-people/media</sem:subject>
    <sem:predicate>http://www.w3.org/2004/02/skos/core#broader</sem:predicate>
    <sem:object datatype="sem:iri">http://www.lds.org/vrl/specific-people/media/duzette-edward-p</sem:object>
  </sem:triple>
  <sem:triple>
    <sem:subject>http://www.lds.org/vrl/specific-people/media</sem:subject>
    <sem:predicate>http://www.w3.org/2004/02/skos/core#broader</sem:predicate>
    <sem:object datatype="sem:iri">http://www.lds.org/vrl/specific-people/media/dvarionas-justus</sem:object>
  </sem:triple>
  <sem:triple>
    <sem:subject>http://www.lds.org/vrl/specific-people/media</sem:subject>
    <sem:predicate>http://www.w3.org/2004/02/skos/core#broader</sem:predicate>
    <sem:object datatype="sem:iri">http://www.lds.org/vrl/specific-people/media/eder-linda</sem:object>
  </sem:triple>
  <sem:triple>
    <sem:subject>http://www.lds.org/vrl/specific-people/media</sem:subject>
    <sem:predicate>http://www.w3.org/2004/02/skos/core#broader</sem:predicate>
    <sem:object datatype="sem:iri">http://www.lds.org/vrl/specific-people/media/elliott-richard-l</sem:object>
  </sem:triple>
  <sem:triple>
    <sem:subject>http://www.lds.org/vrl/specific-people/media</sem:subject>
    <sem:predicate>http://www.w3.org/2004/02/skos/core#broader</sem:predicate>
    <sem:object datatype="sem:iri">http://www.lds.org/vrl/specific-people/media/emile-mark</sem:object>
  </sem:triple>
  <sem:triple>
    <sem:subject>http://www.lds.org/vrl/specific-people/media</sem:subject>
    <sem:predicate>http://www.w3.org/2004/02/skos/core#broader</sem:predicate>
    <sem:object datatype="sem:iri">http://www.lds.org/vrl/specific-people/media/evans-oakley-s</sem:object>
  </sem:triple>
  <sem:triple>
    <sem:subject>http://www.lds.org/vrl/specific-people/media</sem:subject>
    <sem:predicate>http://www.w3.org/2004/02/skos/core#broader</sem:predicate>
    <sem:object datatype="sem:iri">http://www.lds.org/vrl/specific-people/media/fleming-renee</sem:object>
  </sem:triple>
  <sem:triple>
    <sem:subject>http://www.lds.org/vrl/specific-people/media</sem:subject>
    <sem:predicate>http://www.w3.org/2004/02/skos/core#broader</sem:predicate>
    <sem:object datatype="sem:iri">http://www.lds.org/vrl/specific-people/media/frogley-jenny-jordan</sem:object>
  </sem:triple>
  <sem:triple>
    <sem:subject>http://www.lds.org/vrl/specific-people/media</sem:subject>
    <sem:predicate>http://www.w3.org/2004/02/skos/core#broader</sem:predicate>
    <sem:object datatype="sem:iri">http://www.lds.org/vrl/specific-people/media/gardner-joy-r</sem:object>
  </sem:triple>
  <sem:triple>
    <sem:subject>http://www.lds.org/vrl/specific-people/media</sem:subject>
    <sem:predicate>http://www.w3.org/2004/02/skos/core#broader</sem:predicate>
    <sem:object datatype="sem:iri">http://www.lds.org/vrl/specific-people/media/garrett-angela</sem:object>
  </sem:triple>
  <sem:triple>
    <sem:subject>http://www.lds.org/vrl/specific-people/media</sem:subject>
    <sem:predicate>http://www.w3.org/2004/02/skos/core#broader</sem:predicate>
    <sem:object datatype="sem:iri">http://www.lds.org/vrl/specific-people/media/gates-brigham-cecil-1887-1941</sem:object>
  </sem:triple>
  <sem:triple>
    <sem:subject>http://www.lds.org/vrl/specific-people/media</sem:subject>
    <sem:predicate>http://www.w3.org/2004/02/skos/core#broader</sem:predicate>
    <sem:object datatype="sem:iri">http://www.lds.org/vrl/specific-people/media/gates-crawford</sem:object>
  </sem:triple>
  <sem:triple>
    <sem:subject>http://www.lds.org/vrl/specific-people/media</sem:subject>
    <sem:predicate>http://www.w3.org/2004/02/skos/core#broader</sem:predicate>
    <sem:object datatype="sem:iri">http://www.lds.org/vrl/specific-people/media/gibbons-annalyse</sem:object>
  </sem:triple>
  <sem:triple>
    <sem:subject>http://www.lds.org/vrl/specific-people/media</sem:subject>
    <sem:predicate>http://www.w3.org/2004/02/skos/core#broader</sem:predicate>
    <sem:object datatype="sem:iri">http://www.lds.org/vrl/specific-people/media/gibbons-aubrea</sem:object>
  </sem:triple>
  <sem:triple>
    <sem:subject>http://www.lds.org/vrl/specific-people/media</sem:subject>
    <sem:predicate>http://www.w3.org/2004/02/skos/core#broader</sem:predicate>
    <sem:object datatype="sem:iri">http://www.lds.org/vrl/specific-people/media/gibbons-barry</sem:object>
  </sem:triple>
  <sem:triple>
    <sem:subject>http://www.lds.org/vrl/specific-people/media</sem:subject>
    <sem:predicate>http://www.w3.org/2004/02/skos/core#broader</sem:predicate>
    <sem:object datatype="sem:iri">http://www.lds.org/vrl/specific-people/media/gibbons-grant</sem:object>
  </sem:triple>
  <sem:triple>
    <sem:subject>http://www.lds.org/vrl/specific-people/media</sem:subject>
    <sem:predicate>http://www.w3.org/2004/02/skos/core#broader</sem:predicate>
    <sem:object datatype="sem:iri">http://www.lds.org/vrl/specific-people/media/gibbons-lucie</sem:object>
  </sem:triple>
  <sem:triple>
    <sem:subject>http://www.lds.org/vrl/specific-people/media</sem:subject>
    <sem:predicate>http://www.w3.org/2004/02/skos/core#broader</sem:predicate>
    <sem:object datatype="sem:iri">http://www.lds.org/vrl/specific-people/media/gibbons-michael</sem:object>
  </sem:triple>
  <sem:triple>
    <sem:subject>http://www.lds.org/vrl/specific-people/media</sem:subject>
    <sem:predicate>http://www.w3.org/2004/02/skos/core#broader</sem:predicate>
    <sem:object datatype="sem:iri">http://www.lds.org/vrl/specific-people/media/glade-earl-joseph-1911-2001</sem:object>
  </sem:triple>
  <sem:triple>
    <sem:subject>http://www.lds.org/vrl/specific-people/media</sem:subject>
    <sem:predicate>http://www.w3.org/2004/02/skos/core#broader</sem:predicate>
    <sem:object datatype="sem:iri">http://www.lds.org/vrl/specific-people/media/goeckeritz-jeannine</sem:object>
  </sem:triple>
  <sem:triple>
    <sem:subject>http://www.lds.org/vrl/specific-people/media</sem:subject>
    <sem:predicate>http://www.w3.org/2004/02/skos/core#broader</sem:predicate>
    <sem:object datatype="sem:iri">http://www.lds.org/vrl/specific-people/media/goodliffe-bonnie</sem:object>
  </sem:triple>
  <sem:triple>
    <sem:subject>http://www.lds.org/vrl/specific-people/media</sem:subject>
    <sem:predicate>http://www.w3.org/2004/02/skos/core#broader</sem:predicate>
    <sem:object datatype="sem:iri">http://www.lds.org/vrl/specific-people/media/goodwin-steuart</sem:object>
  </sem:triple>
  <sem:triple>
    <sem:subject>http://www.lds.org/vrl/specific-people/media</sem:subject>
    <sem:predicate>http://www.w3.org/2004/02/skos/core#broader</sem:predicate>
    <sem:object datatype="sem:iri">http://www.lds.org/vrl/specific-people/media/graham-othalie</sem:object>
  </sem:triple>
  <sem:triple>
    <sem:subject>http://www.lds.org/vrl/specific-people/media</sem:subject>
    <sem:predicate>http://www.w3.org/2004/02/skos/core#broader</sem:predicate>
    <sem:object datatype="sem:iri">http://www.lds.org/vrl/specific-people/media/graves-denyce</sem:object>
  </sem:triple>
  <sem:triple>
    <sem:subject>http://www.lds.org/vrl/specific-people/media</sem:subject>
    <sem:predicate>http://www.w3.org/2004/02/skos/core#broader</sem:predicate>
    <sem:object datatype="sem:iri">http://www.lds.org/vrl/specific-people/media/graves-peter-1926-2010</sem:object>
  </sem:triple>
  <sem:triple>
    <sem:subject>http://www.lds.org/vrl/specific-people/media</sem:subject>
    <sem:predicate>http://www.w3.org/2004/02/skos/core#broader</sem:predicate>
    <sem:object datatype="sem:iri">http://www.lds.org/vrl/specific-people/media/gregory-herold</sem:object>
  </sem:triple>
  <sem:triple>
    <sem:subject>http://www.lds.org/vrl/specific-people/media</sem:subject>
    <sem:predicate>http://www.w3.org/2004/02/skos/core#broader</sem:predicate>
    <sem:object datatype="sem:iri">http://www.lds.org/vrl/specific-people/media/griggs-thomas-cott-1845-1903</sem:object>
  </sem:triple>
  <sem:triple>
    <sem:subject>http://www.lds.org/vrl/specific-people/media</sem:subject>
    <sem:predicate>http://www.w3.org/2004/02/skos/core#broader</sem:predicate>
    <sem:object datatype="sem:iri">http://www.lds.org/vrl/specific-people/media/gritton-bonie</sem:object>
  </sem:triple>
  <sem:triple>
    <sem:subject>http://www.lds.org/vrl/specific-people/media</sem:subject>
    <sem:predicate>http://www.w3.org/2004/02/skos/core#broader</sem:predicate>
    <sem:object datatype="sem:iri">http://www.lds.org/vrl/specific-people/media/gruppman-igor</sem:object>
  </sem:triple>
  <sem:triple>
    <sem:subject>http://www.lds.org/vrl/specific-people/media</sem:subject>
    <sem:predicate>http://www.w3.org/2004/02/skos/core#broader</sem:predicate>
    <sem:object datatype="sem:iri">http://www.lds.org/vrl/specific-people/media/gruppman-vesna</sem:object>
  </sem:triple>
  <sem:triple>
    <sem:subject>http://www.lds.org/vrl/specific-people/media</sem:subject>
    <sem:predicate>http://www.w3.org/2004/02/skos/core#broader</sem:predicate>
    <sem:object datatype="sem:iri">http://www.lds.org/vrl/specific-people/media/gunn-nathan</sem:object>
  </sem:triple>
  <sem:triple>
    <sem:subject>http://www.lds.org/vrl/specific-people/media</sem:subject>
    <sem:predicate>http://www.w3.org/2004/02/skos/core#broader</sem:predicate>
    <sem:object datatype="sem:iri">http://www.lds.org/vrl/specific-people/media/hagen-will</sem:object>
  </sem:triple>
  <sem:triple>
    <sem:subject>http://www.lds.org/vrl/specific-people/media</sem:subject>
    <sem:predicate>http://www.w3.org/2004/02/skos/core#broader</sem:predicate>
    <sem:object datatype="sem:iri">http://www.lds.org/vrl/specific-people/media/handel-george-frideric</sem:object>
  </sem:triple>
  <sem:triple>
    <sem:subject>http://www.lds.org/vrl/specific-people/media</sem:subject>
    <sem:predicate>http://www.w3.org/2004/02/skos/core#broader</sem:predicate>
    <sem:object datatype="sem:iri">http://www.lds.org/vrl/specific-people/media/hardink-jason</sem:object>
  </sem:triple>
  <sem:triple>
    <sem:subject>http://www.lds.org/vrl/specific-people/media</sem:subject>
    <sem:predicate>http://www.w3.org/2004/02/skos/core#broader</sem:predicate>
    <sem:object datatype="sem:iri">http://www.lds.org/vrl/specific-people/media/hawkes-sharlene</sem:object>
  </sem:triple>
  <sem:triple>
    <sem:subject>http://www.lds.org/vrl/specific-people/media</sem:subject>
    <sem:predicate>http://www.w3.org/2004/02/skos/core#broader</sem:predicate>
    <sem:object datatype="sem:iri">http://www.lds.org/vrl/specific-people/media/hell-felix-1985-organist</sem:object>
  </sem:triple>
  <sem:triple>
    <sem:subject>http://www.lds.org/vrl/specific-people/media</sem:subject>
    <sem:predicate>http://www.w3.org/2004/02/skos/core#broader</sem:predicate>
    <sem:object datatype="sem:iri">http://www.lds.org/vrl/specific-people/media/herrmann-edward-kirk-1943</sem:object>
  </sem:triple>
  <sem:triple>
    <sem:subject>http://www.lds.org/vrl/specific-people/media</sem:subject>
    <sem:predicate>http://www.w3.org/2004/02/skos/core#broader</sem:predicate>
    <sem:object datatype="sem:iri">http://www.lds.org/vrl/specific-people/media/heslop-j-malan-1923-2011</sem:object>
  </sem:triple>
  <sem:triple>
    <sem:subject>http://www.lds.org/vrl/specific-people/media</sem:subject>
    <sem:predicate>http://www.w3.org/2004/02/skos/core#broader</sem:predicate>
    <sem:object datatype="sem:iri">http://www.lds.org/vrl/specific-people/media/holbrook-hillary</sem:object>
  </sem:triple>
  <sem:triple>
    <sem:subject>http://www.lds.org/vrl/specific-people/media</sem:subject>
    <sem:predicate>http://www.w3.org/2004/02/skos/core#broader</sem:predicate>
    <sem:object datatype="sem:iri">http://www.lds.org/vrl/specific-people/media/holmes-christopher</sem:object>
  </sem:triple>
  <sem:triple>
    <sem:subject>http://www.lds.org/vrl/specific-people/media</sem:subject>
    <sem:predicate>http://www.w3.org/2004/02/skos/core#broader</sem:predicate>
    <sem:object datatype="sem:iri">http://www.lds.org/vrl/specific-people/media/honma-tamami</sem:object>
  </sem:triple>
  <sem:triple>
    <sem:subject>http://www.lds.org/vrl/specific-people/media</sem:subject>
    <sem:predicate>http://www.w3.org/2004/02/skos/core#broader</sem:predicate>
    <sem:object datatype="sem:iri">http://www.lds.org/vrl/specific-people/media/hurtado-isaac</sem:object>
  </sem:triple>
  <sem:triple>
    <sem:subject>http://www.lds.org/vrl/specific-people/media</sem:subject>
    <sem:predicate>http://www.w3.org/2004/02/skos/core#broader</sem:predicate>
    <sem:object datatype="sem:iri">http://www.lds.org/vrl/specific-people/media/itin-ilya</sem:object>
  </sem:triple>
  <sem:triple>
    <sem:subject>http://www.lds.org/vrl/specific-people/media</sem:subject>
    <sem:predicate>http://www.w3.org/2004/02/skos/core#broader</sem:predicate>
    <sem:object datatype="sem:iri">http://www.lds.org/vrl/specific-people/media/jacobs-david-kent-1937</sem:object>
  </sem:triple>
  <sem:triple>
    <sem:subject>http://www.lds.org/vrl/specific-people/media</sem:subject>
    <sem:predicate>http://www.w3.org/2004/02/skos/core#broader</sem:predicate>
    <sem:object datatype="sem:iri">http://www.lds.org/vrl/specific-people/media/jemison-keisker-lynn</sem:object>
  </sem:triple>
  <sem:triple>
    <sem:subject>http://www.lds.org/vrl/specific-people/media</sem:subject>
    <sem:predicate>http://www.w3.org/2004/02/skos/core#broader</sem:predicate>
    <sem:object datatype="sem:iri">http://www.lds.org/vrl/specific-people/media/jessop-craig</sem:object>
  </sem:triple>
  <sem:triple>
    <sem:subject>http://www.lds.org/vrl/specific-people/media</sem:subject>
    <sem:predicate>http://www.w3.org/2004/02/skos/core#broader</sem:predicate>
    <sem:object datatype="sem:iri">http://www.lds.org/vrl/specific-people/media/killian-lindsey-robinson</sem:object>
  </sem:triple>
  <sem:triple>
    <sem:subject>http://www.lds.org/vrl/specific-people/media</sem:subject>
    <sem:predicate>http://www.w3.org/2004/02/skos/core#broader</sem:predicate>
    <sem:object datatype="sem:iri">http://www.lds.org/vrl/specific-people/media/kim-mi-kyung</sem:object>
  </sem:triple>
  <sem:triple>
    <sem:subject>http://www.lds.org/vrl/specific-people/media</sem:subject>
    <sem:predicate>http://www.w3.org/2004/02/skos/core#broader</sem:predicate>
    <sem:object datatype="sem:iri">http://www.lds.org/vrl/specific-people/media/kimball-edward-partridge-1882-1937</sem:object>
  </sem:triple>
  <sem:triple>
    <sem:subject>http://www.lds.org/vrl/specific-people/media</sem:subject>
    <sem:predicate>http://www.w3.org/2004/02/skos/core#broader</sem:predicate>
    <sem:object datatype="sem:iri">http://www.lds.org/vrl/specific-people/media/kinard-j-spencer</sem:object>
  </sem:triple>
  <sem:triple>
    <sem:subject>http://www.lds.org/vrl/specific-people/media</sem:subject>
    <sem:predicate>http://www.w3.org/2004/02/skos/core#broader</sem:predicate>
    <sem:object datatype="sem:iri">http://www.lds.org/vrl/specific-people/media/king-larry</sem:object>
  </sem:triple>
  <sem:triple>
    <sem:subject>http://www.lds.org/vrl/specific-people/media</sem:subject>
    <sem:predicate>http://www.w3.org/2004/02/skos/core#broader</sem:predicate>
    <sem:object datatype="sem:iri">http://www.lds.org/vrl/specific-people/media/knight-gladys</sem:object>
  </sem:triple>
  <sem:triple>
    <sem:subject>http://www.lds.org/vrl/specific-people/media</sem:subject>
    <sem:predicate>http://www.w3.org/2004/02/skos/core#broader</sem:predicate>
    <sem:object datatype="sem:iri">http://www.lds.org/vrl/specific-people/media/kunzel-erich</sem:object>
  </sem:triple>
  <sem:triple>
    <sem:subject>http://www.lds.org/vrl/specific-people/media</sem:subject>
    <sem:predicate>http://www.w3.org/2004/02/skos/core#broader</sem:predicate>
    <sem:object datatype="sem:iri">http://www.lds.org/vrl/specific-people/media/lake-fred</sem:object>
  </sem:triple>
  <sem:triple>
    <sem:subject>http://www.lds.org/vrl/specific-people/media</sem:subject>
    <sem:predicate>http://www.w3.org/2004/02/skos/core#broader</sem:predicate>
    <sem:object datatype="sem:iri">http://www.lds.org/vrl/specific-people/media/lansbury-angela</sem:object>
  </sem:triple>
  <sem:triple>
    <sem:subject>http://www.lds.org/vrl/specific-people/media</sem:subject>
    <sem:predicate>http://www.w3.org/2004/02/skos/core#broader</sem:predicate>
    <sem:object datatype="sem:iri">http://www.lds.org/vrl/specific-people/media/lewis-laura-garff</sem:object>
  </sem:triple>
  <sem:triple>
    <sem:subject>http://www.lds.org/vrl/specific-people/media</sem:subject>
    <sem:predicate>http://www.w3.org/2004/02/skos/core#broader</sem:predicate>
    <sem:object datatype="sem:iri">http://www.lds.org/vrl/specific-people/media/liriel-brazilian-performer</sem:object>
  </sem:triple>
  <sem:triple>
    <sem:subject>http://www.lds.org/vrl/specific-people/media</sem:subject>
    <sem:predicate>http://www.w3.org/2004/02/skos/core#broader</sem:predicate>
    <sem:object datatype="sem:iri">http://www.lds.org/vrl/specific-people/media/lockhart-keith</sem:object>
  </sem:triple>
  <sem:triple>
    <sem:subject>http://www.lds.org/vrl/specific-people/media</sem:subject>
    <sem:predicate>http://www.w3.org/2004/02/skos/core#broader</sem:predicate>
    <sem:object datatype="sem:iri">http://www.lds.org/vrl/specific-people/media/longhurst-john</sem:object>
  </sem:triple>
  <sem:triple>
    <sem:subject>http://www.lds.org/vrl/specific-people/media</sem:subject>
    <sem:predicate>http://www.w3.org/2004/02/skos/core#broader</sem:predicate>
    <sem:object datatype="sem:iri">http://www.lds.org/vrl/specific-people/media/lund-anthony-canute-1871-1935</sem:object>
  </sem:triple>
  <sem:triple>
    <sem:subject>http://www.lds.org/vrl/specific-people/media</sem:subject>
    <sem:predicate>http://www.w3.org/2004/02/skos/core#broader</sem:predicate>
    <sem:object datatype="sem:iri">http://www.lds.org/vrl/specific-people/media/macneil-robert</sem:object>
  </sem:triple>
  <sem:triple>
    <sem:subject>http://www.lds.org/vrl/specific-people/media</sem:subject>
    <sem:predicate>http://www.w3.org/2004/02/skos/core#broader</sem:predicate>
    <sem:object datatype="sem:iri">http://www.lds.org/vrl/specific-people/media/malkin-channa</sem:object>
  </sem:triple>
  <sem:triple>
    <sem:subject>http://www.lds.org/vrl/specific-people/media</sem:subject>
    <sem:predicate>http://www.w3.org/2004/02/skos/core#broader</sem:predicate>
    <sem:object datatype="sem:iri">http://www.lds.org/vrl/specific-people/media/margetts-linda</sem:object>
  </sem:triple>
  <sem:triple>
    <sem:subject>http://www.lds.org/vrl/specific-people/media</sem:subject>
    <sem:predicate>http://www.w3.org/2004/02/skos/core#broader</sem:predicate>
    <sem:object datatype="sem:iri">http://www.lds.org/vrl/specific-people/media/mauldin-john</sem:object>
  </sem:triple>
  <sem:triple>
    <sem:subject>http://www.lds.org/vrl/specific-people/media</sem:subject>
    <sem:predicate>http://www.w3.org/2004/02/skos/core#broader</sem:predicate>
    <sem:object datatype="sem:iri">http://www.lds.org/vrl/specific-people/media/mccelland-j-j</sem:object>
  </sem:triple>
  <sem:triple>
    <sem:subject>http://www.lds.org/vrl/specific-people/media</sem:subject>
    <sem:predicate>http://www.w3.org/2004/02/skos/core#broader</sem:predicate>
    <sem:object datatype="sem:iri">http://www.lds.org/vrl/specific-people/media/mcclellan-john-jasper-1874-1925</sem:object>
  </sem:triple>
  <sem:triple>
    <sem:subject>http://www.lds.org/vrl/specific-people/media</sem:subject>
    <sem:predicate>http://www.w3.org/2004/02/skos/core#broader</sem:predicate>
    <sem:object datatype="sem:iri">http://www.lds.org/vrl/specific-people/media/mcdonald-audra</sem:object>
  </sem:triple>
  <sem:triple>
    <sem:subject>http://www.lds.org/vrl/specific-people/media</sem:subject>
    <sem:predicate>http://www.w3.org/2004/02/skos/core#broader</sem:predicate>
    <sem:object datatype="sem:iri">http://www.lds.org/vrl/specific-people/media/mclean-michael</sem:object>
  </sem:triple>
  <sem:triple>
    <sem:subject>http://www.lds.org/vrl/specific-people/media</sem:subject>
    <sem:predicate>http://www.w3.org/2004/02/skos/core#broader</sem:predicate>
    <sem:object datatype="sem:iri">http://www.lds.org/vrl/specific-people/media/melba-nellie-dame-1861-1931</sem:object>
  </sem:triple>
  <sem:triple>
    <sem:subject>http://www.lds.org/vrl/specific-people/media</sem:subject>
    <sem:predicate>http://www.w3.org/2004/02/skos/core#broader</sem:predicate>
    <sem:object datatype="sem:iri">http://www.lds.org/vrl/specific-people/media/mendelssohn-bartholdy-felix-1809-1847</sem:object>
  </sem:triple>
  <sem:triple>
    <sem:subject>http://www.lds.org/vrl/specific-people/media</sem:subject>
    <sem:predicate>http://www.w3.org/2004/02/skos/core#broader</sem:predicate>
    <sem:object datatype="sem:iri">http://www.lds.org/vrl/specific-people/media/meredith-steve</sem:object>
  </sem:triple>
  <sem:triple>
    <sem:subject>http://www.lds.org/vrl/specific-people/media</sem:subject>
    <sem:predicate>http://www.w3.org/2004/02/skos/core#broader</sem:predicate>
    <sem:object datatype="sem:iri">http://www.lds.org/vrl/specific-people/media/miller-scott</sem:object>
  </sem:triple>
  <sem:triple>
    <sem:subject>http://www.lds.org/vrl/specific-people/media</sem:subject>
    <sem:predicate>http://www.w3.org/2004/02/skos/core#broader</sem:predicate>
    <sem:object datatype="sem:iri">http://www.lds.org/vrl/specific-people/media/mitchell-brian-stokes</sem:object>
  </sem:triple>
  <sem:triple>
    <sem:subject>http://www.lds.org/vrl/specific-people/media</sem:subject>
    <sem:predicate>http://www.w3.org/2004/02/skos/core#broader</sem:predicate>
    <sem:object datatype="sem:iri">http://www.lds.org/vrl/specific-people/media/mitchell-nephi-lorenzo-1889</sem:object>
  </sem:triple>
  <sem:triple>
    <sem:subject>http://www.lds.org/vrl/specific-people/media</sem:subject>
    <sem:predicate>http://www.w3.org/2004/02/skos/core#broader</sem:predicate>
    <sem:object datatype="sem:iri">http://www.lds.org/vrl/specific-people/media/monroe-marilyn</sem:object>
  </sem:triple>
  <sem:triple>
    <sem:subject>http://www.lds.org/vrl/specific-people/media</sem:subject>
    <sem:predicate>http://www.w3.org/2004/02/skos/core#broader</sem:predicate>
    <sem:object datatype="sem:iri">http://www.lds.org/vrl/specific-people/media/moody-michael-f</sem:object>
  </sem:triple>
  <sem:triple>
    <sem:subject>http://www.lds.org/vrl/specific-people/media</sem:subject>
    <sem:predicate>http://www.w3.org/2004/02/skos/core#broader</sem:predicate>
    <sem:object datatype="sem:iri">http://www.lds.org/vrl/specific-people/media/morgan-jared</sem:object>
  </sem:triple>
  <sem:triple>
    <sem:subject>http://www.lds.org/vrl/specific-people/media</sem:subject>
    <sem:predicate>http://www.w3.org/2004/02/skos/core#broader</sem:predicate>
    <sem:object datatype="sem:iri">http://www.lds.org/vrl/specific-people/media/murdock-elizabeth</sem:object>
  </sem:triple>
  <sem:triple>
    <sem:subject>http://www.lds.org/vrl/specific-people/media</sem:subject>
    <sem:predicate>http://www.w3.org/2004/02/skos/core#broader</sem:predicate>
    <sem:object datatype="sem:iri">http://www.lds.org/vrl/specific-people/media/murphy-ryan</sem:object>
  </sem:triple>
  <sem:triple>
    <sem:subject>http://www.lds.org/vrl/specific-people/media</sem:subject>
    <sem:predicate>http://www.w3.org/2004/02/skos/core#broader</sem:predicate>
    <sem:object datatype="sem:iri">http://www.lds.org/vrl/specific-people/media/newell-lloyd</sem:object>
  </sem:triple>
  <sem:triple>
    <sem:subject>http://www.lds.org/vrl/specific-people/media</sem:subject>
    <sem:predicate>http://www.w3.org/2004/02/skos/core#broader</sem:predicate>
    <sem:object datatype="sem:iri">http://www.lds.org/vrl/specific-people/media/oliphant-tyler</sem:object>
  </sem:triple>
  <sem:triple>
    <sem:subject>http://www.lds.org/vrl/specific-people/media</sem:subject>
    <sem:predicate>http://www.w3.org/2004/02/skos/core#broader</sem:predicate>
    <sem:object datatype="sem:iri">http://www.lds.org/vrl/specific-people/media/olsen-stanford</sem:object>
  </sem:triple>
  <sem:triple>
    <sem:subject>http://www.lds.org/vrl/specific-people/media</sem:subject>
    <sem:predicate>http://www.w3.org/2004/02/skos/core#broader</sem:predicate>
    <sem:object datatype="sem:iri">http://www.lds.org/vrl/specific-people/media/osmond-alan</sem:object>
  </sem:triple>
  <sem:triple>
    <sem:subject>http://www.lds.org/vrl/specific-people/media</sem:subject>
    <sem:predicate>http://www.w3.org/2004/02/skos/core#broader</sem:predicate>
    <sem:object datatype="sem:iri">http://www.lds.org/vrl/specific-people/media/osmond-donny</sem:object>
  </sem:triple>
  <sem:triple>
    <sem:subject>http://www.lds.org/vrl/specific-people/media</sem:subject>
    <sem:predicate>http://www.w3.org/2004/02/skos/core#broader</sem:predicate>
    <sem:object datatype="sem:iri">http://www.lds.org/vrl/specific-people/media/osmond-jay</sem:object>
  </sem:triple>
  <sem:triple>
    <sem:subject>http://www.lds.org/vrl/specific-people/media</sem:subject>
    <sem:predicate>http://www.w3.org/2004/02/skos/core#broader</sem:predicate>
    <sem:object datatype="sem:iri">http://www.lds.org/vrl/specific-people/media/osmond-jimmy</sem:object>
  </sem:triple>
  <sem:triple>
    <sem:subject>http://www.lds.org/vrl/specific-people/media</sem:subject>
    <sem:predicate>http://www.w3.org/2004/02/skos/core#broader</sem:predicate>
    <sem:object datatype="sem:iri">http://www.lds.org/vrl/specific-people/media/osmond-marie</sem:object>
  </sem:triple>
  <sem:triple>
    <sem:subject>http://www.lds.org/vrl/specific-people/media</sem:subject>
    <sem:predicate>http://www.w3.org/2004/02/skos/core#broader</sem:predicate>
    <sem:object datatype="sem:iri">http://www.lds.org/vrl/specific-people/media/osmond-merrill</sem:object>
  </sem:triple>
  <sem:triple>
    <sem:subject>http://www.lds.org/vrl/specific-people/media</sem:subject>
    <sem:predicate>http://www.w3.org/2004/02/skos/core#broader</sem:predicate>
    <sem:object datatype="sem:iri">http://www.lds.org/vrl/specific-people/media/osmond-tom</sem:object>
  </sem:triple>
  <sem:triple>
    <sem:subject>http://www.lds.org/vrl/specific-people/media</sem:subject>
    <sem:predicate>http://www.w3.org/2004/02/skos/core#broader</sem:predicate>
    <sem:object datatype="sem:iri">http://www.lds.org/vrl/specific-people/media/osmond-virl</sem:object>
  </sem:triple>
  <sem:triple>
    <sem:subject>http://www.lds.org/vrl/specific-people/media</sem:subject>
    <sem:predicate>http://www.w3.org/2004/02/skos/core#broader</sem:predicate>
    <sem:object datatype="sem:iri">http://www.lds.org/vrl/specific-people/media/osmond-wayne</sem:object>
  </sem:triple>
  <sem:triple>
    <sem:subject>http://www.lds.org/vrl/specific-people/media</sem:subject>
    <sem:predicate>http://www.w3.org/2004/02/skos/core#broader</sem:predicate>
    <sem:object datatype="sem:iri">http://www.lds.org/vrl/specific-people/media/oswald-tamara</sem:object>
  </sem:triple>
  <sem:triple>
    <sem:subject>http://www.lds.org/vrl/specific-people/media</sem:subject>
    <sem:predicate>http://www.w3.org/2004/02/skos/core#broader</sem:predicate>
    <sem:object datatype="sem:iri">http://www.lds.org/vrl/specific-people/media/ottley-jerold-d</sem:object>
  </sem:triple>
  <sem:triple>
    <sem:subject>http://www.lds.org/vrl/specific-people/media</sem:subject>
    <sem:predicate>http://www.w3.org/2004/02/skos/core#broader</sem:predicate>
    <sem:object datatype="sem:iri">http://www.lds.org/vrl/specific-people/media/ottley-joann</sem:object>
  </sem:triple>
  <sem:triple>
    <sem:subject>http://www.lds.org/vrl/specific-people/media</sem:subject>
    <sem:predicate>http://www.w3.org/2004/02/skos/core#broader</sem:predicate>
    <sem:object datatype="sem:iri">http://www.lds.org/vrl/specific-people/media/pace-gerald</sem:object>
  </sem:triple>
  <sem:triple>
    <sem:subject>http://www.lds.org/vrl/specific-people/media</sem:subject>
    <sem:predicate>http://www.w3.org/2004/02/skos/core#broader</sem:predicate>
    <sem:object datatype="sem:iri">http://www.lds.org/vrl/specific-people/media/patterson-louis</sem:object>
  </sem:triple>
  <sem:triple>
    <sem:subject>http://www.lds.org/vrl/specific-people/media</sem:subject>
    <sem:predicate>http://www.w3.org/2004/02/skos/core#broader</sem:predicate>
    <sem:object datatype="sem:iri">http://www.lds.org/vrl/specific-people/media/patty-sandi</sem:object>
  </sem:triple>
  <sem:triple>
    <sem:subject>http://www.lds.org/vrl/specific-people/media</sem:subject>
    <sem:predicate>http://www.w3.org/2004/02/skos/core#broader</sem:predicate>
    <sem:object datatype="sem:iri">http://www.lds.org/vrl/specific-people/media/paulsen-charlotte</sem:object>
  </sem:triple>
  <sem:triple>
    <sem:subject>http://www.lds.org/vrl/specific-people/media</sem:subject>
    <sem:predicate>http://www.w3.org/2004/02/skos/core#broader</sem:predicate>
    <sem:object datatype="sem:iri">http://www.lds.org/vrl/specific-people/media/pegram-ryan</sem:object>
  </sem:triple>
  <sem:triple>
    <sem:subject>http://www.lds.org/vrl/specific-people/media</sem:subject>
    <sem:predicate>http://www.w3.org/2004/02/skos/core#broader</sem:predicate>
    <sem:object datatype="sem:iri">http://www.lds.org/vrl/specific-people/media/perry-janice-kapp</sem:object>
  </sem:triple>
  <sem:triple>
    <sem:subject>http://www.lds.org/vrl/specific-people/media</sem:subject>
    <sem:predicate>http://www.w3.org/2004/02/skos/core#broader</sem:predicate>
    <sem:object datatype="sem:iri">http://www.lds.org/vrl/specific-people/media/petersen-stewart-d-1960</sem:object>
  </sem:triple>
  <sem:triple>
    <sem:subject>http://www.lds.org/vrl/specific-people/media</sem:subject>
    <sem:predicate>http://www.w3.org/2004/02/skos/core#broader</sem:predicate>
    <sem:object datatype="sem:iri">http://www.lds.org/vrl/specific-people/media/peterson-robert</sem:object>
  </sem:triple>
  <sem:triple>
    <sem:subject>http://www.lds.org/vrl/specific-people/media</sem:subject>
    <sem:predicate>http://www.w3.org/2004/02/skos/core#broader</sem:predicate>
    <sem:object datatype="sem:iri">http://www.lds.org/vrl/specific-people/media/phillips-jenny</sem:object>
  </sem:triple>
  <sem:triple>
    <sem:subject>http://www.lds.org/vrl/specific-people/media</sem:subject>
    <sem:predicate>http://www.w3.org/2004/02/skos/core#broader</sem:predicate>
    <sem:object datatype="sem:iri">http://www.lds.org/vrl/specific-people/media/poulsen-udell-e</sem:object>
  </sem:triple>
  <sem:triple>
    <sem:subject>http://www.lds.org/vrl/specific-people/media</sem:subject>
    <sem:predicate>http://www.w3.org/2004/02/skos/core#broader</sem:predicate>
    <sem:object datatype="sem:iri">http://www.lds.org/vrl/specific-people/media/prats-jorge-luis</sem:object>
  </sem:triple>
  <sem:triple>
    <sem:subject>http://www.lds.org/vrl/specific-people/media</sem:subject>
    <sem:predicate>http://www.w3.org/2004/02/skos/core#broader</sem:predicate>
    <sem:object datatype="sem:iri">http://www.lds.org/vrl/specific-people/media/quesada-roy</sem:object>
  </sem:triple>
  <sem:triple>
    <sem:subject>http://www.lds.org/vrl/specific-people/media</sem:subject>
    <sem:predicate>http://www.w3.org/2004/02/skos/core#broader</sem:predicate>
    <sem:object datatype="sem:iri">http://www.lds.org/vrl/specific-people/media/randle-cammon</sem:object>
  </sem:triple>
  <sem:triple>
    <sem:subject>http://www.lds.org/vrl/specific-people/media</sem:subject>
    <sem:predicate>http://www.w3.org/2004/02/skos/core#broader</sem:predicate>
    <sem:object datatype="sem:iri">http://www.lds.org/vrl/specific-people/media/riplinger-donald-w</sem:object>
  </sem:triple>
  <sem:triple>
    <sem:subject>http://www.lds.org/vrl/specific-people/media</sem:subject>
    <sem:predicate>http://www.w3.org/2004/02/skos/core#broader</sem:predicate>
    <sem:object datatype="sem:iri">http://www.lds.org/vrl/specific-people/media/rishoi-stacy</sem:object>
  </sem:triple>
  <sem:triple>
    <sem:subject>http://www.lds.org/vrl/specific-people/media</sem:subject>
    <sem:predicate>http://www.w3.org/2004/02/skos/core#broader</sem:predicate>
    <sem:object datatype="sem:iri">http://www.lds.org/vrl/specific-people/media/robertson-leroy-j</sem:object>
  </sem:triple>
  <sem:triple>
    <sem:subject>http://www.lds.org/vrl/specific-people/media</sem:subject>
    <sem:predicate>http://www.w3.org/2004/02/skos/core#broader</sem:predicate>
    <sem:object datatype="sem:iri">http://www.lds.org/vrl/specific-people/media/robinson-morris-d</sem:object>
  </sem:triple>
  <sem:triple>
    <sem:subject>http://www.lds.org/vrl/specific-people/media</sem:subject>
    <sem:predicate>http://www.w3.org/2004/02/skos/core#broader</sem:predicate>
    <sem:object datatype="sem:iri">http://www.lds.org/vrl/specific-people/media/rohde-julie</sem:object>
  </sem:triple>
  <sem:triple>
    <sem:subject>http://www.lds.org/vrl/specific-people/media</sem:subject>
    <sem:predicate>http://www.w3.org/2004/02/skos/core#broader</sem:predicate>
    <sem:object datatype="sem:iri">http://www.lds.org/vrl/specific-people/media/santos-gerson</sem:object>
  </sem:triple>
  <sem:triple>
    <sem:subject>http://www.lds.org/vrl/specific-people/media</sem:subject>
    <sem:predicate>http://www.w3.org/2004/02/skos/core#broader</sem:predicate>
    <sem:object datatype="sem:iri">http://www.lds.org/vrl/specific-people/media/schreiner-alexander</sem:object>
  </sem:triple>
  <sem:triple>
    <sem:subject>http://www.lds.org/vrl/specific-people/media</sem:subject>
    <sem:predicate>http://www.w3.org/2004/02/skos/core#broader</sem:predicate>
    <sem:object datatype="sem:iri">http://www.lds.org/vrl/specific-people/media/schreiner-alexander-ferdinand-1901-1987</sem:object>
  </sem:triple>
  <sem:triple>
    <sem:subject>http://www.lds.org/vrl/specific-people/media</sem:subject>
    <sem:predicate>http://www.w3.org/2004/02/skos/core#broader</sem:predicate>
    <sem:object datatype="sem:iri">http://www.lds.org/vrl/specific-people/media/seymour-jane</sem:object>
  </sem:triple>
  <sem:triple>
    <sem:subject>http://www.lds.org/vrl/specific-people/media</sem:subject>
    <sem:predicate>http://www.w3.org/2004/02/skos/core#broader</sem:predicate>
    <sem:object datatype="sem:iri">http://www.lds.org/vrl/specific-people/media/shafer-celena</sem:object>
  </sem:triple>
  <sem:triple>
    <sem:subject>http://www.lds.org/vrl/specific-people/media</sem:subject>
    <sem:predicate>http://www.w3.org/2004/02/skos/core#broader</sem:predicate>
    <sem:object datatype="sem:iri">http://www.lds.org/vrl/specific-people/media/sham-aristo-1996</sem:object>
  </sem:triple>
  <sem:triple>
    <sem:subject>http://www.lds.org/vrl/specific-people/media</sem:subject>
    <sem:predicate>http://www.w3.org/2004/02/skos/core#broader</sem:predicate>
    <sem:object datatype="sem:iri">http://www.lds.org/vrl/specific-people/media/shelton-chad</sem:object>
  </sem:triple>
  <sem:triple>
    <sem:subject>http://www.lds.org/vrl/specific-people/media</sem:subject>
    <sem:predicate>http://www.w3.org/2004/02/skos/core#broader</sem:predicate>
    <sem:object datatype="sem:iri">http://www.lds.org/vrl/specific-people/media/sims-lori</sem:object>
  </sem:triple>
  <sem:triple>
    <sem:subject>http://www.lds.org/vrl/specific-people/media</sem:subject>
    <sem:predicate>http://www.w3.org/2004/02/skos/core#broader</sem:predicate>
    <sem:object datatype="sem:iri">http://www.lds.org/vrl/specific-people/media/smith-larry</sem:object>
  </sem:triple>
  <sem:triple>
    <sem:subject>http://www.lds.org/vrl/specific-people/media</sem:subject>
    <sem:predicate>http://www.w3.org/2004/02/skos/core#broader</sem:predicate>
    <sem:object datatype="sem:iri">http://www.lds.org/vrl/specific-people/media/squires-chantelle</sem:object>
  </sem:triple>
  <sem:triple>
    <sem:subject>http://www.lds.org/vrl/specific-people/media</sem:subject>
    <sem:predicate>http://www.w3.org/2004/02/skos/core#broader</sem:predicate>
    <sem:object datatype="sem:iri">http://www.lds.org/vrl/specific-people/media/stambaugh-kathryn</sem:object>
  </sem:triple>
  <sem:triple>
    <sem:subject>http://www.lds.org/vrl/specific-people/media</sem:subject>
    <sem:predicate>http://www.w3.org/2004/02/skos/core#broader</sem:predicate>
    <sem:object datatype="sem:iri">http://www.lds.org/vrl/specific-people/media/stephens-evan</sem:object>
  </sem:triple>
  <sem:triple>
    <sem:subject>http://www.lds.org/vrl/specific-people/media</sem:subject>
    <sem:predicate>http://www.w3.org/2004/02/skos/core#broader</sem:predicate>
    <sem:object datatype="sem:iri">http://www.lds.org/vrl/specific-people/media/stephens-evan-1854-1930</sem:object>
  </sem:triple>
  <sem:triple>
    <sem:subject>http://www.lds.org/vrl/specific-people/media</sem:subject>
    <sem:predicate>http://www.w3.org/2004/02/skos/core#broader</sem:predicate>
    <sem:object datatype="sem:iri">http://www.lds.org/vrl/specific-people/media/stewart-james-maitland-1908-1997</sem:object>
  </sem:triple>
  <sem:triple>
    <sem:subject>http://www.lds.org/vrl/specific-people/media</sem:subject>
    <sem:predicate>http://www.w3.org/2004/02/skos/core#broader</sem:predicate>
    <sem:object datatype="sem:iri">http://www.lds.org/vrl/specific-people/media/stewart-jimmy</sem:object>
  </sem:triple>
  <sem:triple>
    <sem:subject>http://www.lds.org/vrl/specific-people/media</sem:subject>
    <sem:predicate>http://www.w3.org/2004/02/skos/core#broader</sem:predicate>
    <sem:object datatype="sem:iri">http://www.lds.org/vrl/specific-people/media/suk-mykola</sem:object>
  </sem:triple>
  <sem:triple>
    <sem:subject>http://www.lds.org/vrl/specific-people/media</sem:subject>
    <sem:predicate>http://www.w3.org/2004/02/skos/core#broader</sem:predicate>
    <sem:object datatype="sem:iri">http://www.lds.org/vrl/specific-people/media/sundberg-gerard</sem:object>
  </sem:triple>
  <sem:triple>
    <sem:subject>http://www.lds.org/vrl/specific-people/media</sem:subject>
    <sem:predicate>http://www.w3.org/2004/02/skos/core#broader</sem:predicate>
    <sem:object datatype="sem:iri">http://www.lds.org/vrl/specific-people/media/terfel-bryn</sem:object>
  </sem:triple>
  <sem:triple>
    <sem:subject>http://www.lds.org/vrl/specific-people/media</sem:subject>
    <sem:predicate>http://www.w3.org/2004/02/skos/core#broader</sem:predicate>
    <sem:object datatype="sem:iri">http://www.lds.org/vrl/specific-people/media/thames-jeanine</sem:object>
  </sem:triple>
  <sem:triple>
    <sem:subject>http://www.lds.org/vrl/specific-people/media</sem:subject>
    <sem:predicate>http://www.w3.org/2004/02/skos/core#broader</sem:predicate>
    <sem:object datatype="sem:iri">http://www.lds.org/vrl/specific-people/media/thomas-charles-john-1832-1919</sem:object>
  </sem:triple>
  <sem:triple>
    <sem:subject>http://www.lds.org/vrl/specific-people/media</sem:subject>
    <sem:predicate>http://www.w3.org/2004/02/skos/core#broader</sem:predicate>
    <sem:object datatype="sem:iri">http://www.lds.org/vrl/specific-people/media/thomas-danny-1914-1991</sem:object>
  </sem:triple>
  <sem:triple>
    <sem:subject>http://www.lds.org/vrl/specific-people/media</sem:subject>
    <sem:predicate>http://www.w3.org/2004/02/skos/core#broader</sem:predicate>
    <sem:object datatype="sem:iri">http://www.lds.org/vrl/specific-people/media/thomas-sara</sem:object>
  </sem:triple>
  <sem:triple>
    <sem:subject>http://www.lds.org/vrl/specific-people/media</sem:subject>
    <sem:predicate>http://www.w3.org/2004/02/skos/core#broader</sem:predicate>
    <sem:object datatype="sem:iri">http://www.lds.org/vrl/specific-people/media/ugorski-eugene</sem:object>
  </sem:triple>
  <sem:triple>
    <sem:subject>http://www.lds.org/vrl/specific-people/media</sem:subject>
    <sem:predicate>http://www.w3.org/2004/02/skos/core#broader</sem:predicate>
    <sem:object datatype="sem:iri">http://www.lds.org/vrl/specific-people/media/unsworth-andrew</sem:object>
  </sem:triple>
  <sem:triple>
    <sem:subject>http://www.lds.org/vrl/specific-people/media</sem:subject>
    <sem:predicate>http://www.w3.org/2004/02/skos/core#broader</sem:predicate>
    <sem:object datatype="sem:iri">http://www.lds.org/vrl/specific-people/media/van-brugge-paul-m</sem:object>
  </sem:triple>
  <sem:triple>
    <sem:subject>http://www.lds.org/vrl/specific-people/media</sem:subject>
    <sem:predicate>http://www.w3.org/2004/02/skos/core#broader</sem:predicate>
    <sem:object datatype="sem:iri">http://www.lds.org/vrl/specific-people/media/von-stade-frederica</sem:object>
  </sem:triple>
  <sem:triple>
    <sem:subject>http://www.lds.org/vrl/specific-people/media</sem:subject>
    <sem:predicate>http://www.w3.org/2004/02/skos/core#broader</sem:predicate>
    <sem:object datatype="sem:iri">http://www.lds.org/vrl/specific-people/media/waldron-thomas</sem:object>
  </sem:triple>
  <sem:triple>
    <sem:subject>http://www.lds.org/vrl/specific-people/media</sem:subject>
    <sem:predicate>http://www.w3.org/2004/02/skos/core#broader</sem:predicate>
    <sem:object datatype="sem:iri">http://www.lds.org/vrl/specific-people/media/wallace-mike</sem:object>
  </sem:triple>
  <sem:triple>
    <sem:subject>http://www.lds.org/vrl/specific-people/media</sem:subject>
    <sem:predicate>http://www.w3.org/2004/02/skos/core#broader</sem:predicate>
    <sem:object datatype="sem:iri">http://www.lds.org/vrl/specific-people/media/warby-shane</sem:object>
  </sem:triple>
  <sem:triple>
    <sem:subject>http://www.lds.org/vrl/specific-people/media</sem:subject>
    <sem:predicate>http://www.w3.org/2004/02/skos/core#broader</sem:predicate>
    <sem:object datatype="sem:iri">http://www.lds.org/vrl/specific-people/media/weeks-hilary</sem:object>
  </sem:triple>
  <sem:triple>
    <sem:subject>http://www.lds.org/vrl/specific-people/media</sem:subject>
    <sem:predicate>http://www.w3.org/2004/02/skos/core#broader</sem:predicate>
    <sem:object datatype="sem:iri">http://www.lds.org/vrl/specific-people/media/weir-gillian</sem:object>
  </sem:triple>
  <sem:triple>
    <sem:subject>http://www.lds.org/vrl/specific-people/media</sem:subject>
    <sem:predicate>http://www.w3.org/2004/02/skos/core#broader</sem:predicate>
    <sem:object datatype="sem:iri">http://www.lds.org/vrl/specific-people/media/welch-jay-evard-1925</sem:object>
  </sem:triple>
  <sem:triple>
    <sem:subject>http://www.lds.org/vrl/specific-people/media</sem:subject>
    <sem:predicate>http://www.w3.org/2004/02/skos/core#broader</sem:predicate>
    <sem:object datatype="sem:iri">http://www.lds.org/vrl/specific-people/media/westberg-david</sem:object>
  </sem:triple>
  <sem:triple>
    <sem:subject>http://www.lds.org/vrl/specific-people/media</sem:subject>
    <sem:predicate>http://www.w3.org/2004/02/skos/core#broader</sem:predicate>
    <sem:object datatype="sem:iri">http://www.lds.org/vrl/specific-people/media/whelan-paul</sem:object>
  </sem:triple>
  <sem:triple>
    <sem:subject>http://www.lds.org/vrl/specific-people/media</sem:subject>
    <sem:predicate>http://www.w3.org/2004/02/skos/core#broader</sem:predicate>
    <sem:object datatype="sem:iri">http://www.lds.org/vrl/specific-people/media/whitaker-max</sem:object>
  </sem:triple>
  <sem:triple>
    <sem:subject>http://www.lds.org/vrl/specific-people/media</sem:subject>
    <sem:predicate>http://www.w3.org/2004/02/skos/core#broader</sem:predicate>
    <sem:object datatype="sem:iri">http://www.lds.org/vrl/specific-people/media/whitaker-nick</sem:object>
  </sem:triple>
  <sem:triple>
    <sem:subject>http://www.lds.org/vrl/specific-people/media</sem:subject>
    <sem:predicate>http://www.w3.org/2004/02/skos/core#broader</sem:predicate>
    <sem:object datatype="sem:iri">http://www.lds.org/vrl/specific-people/media/white-brooke</sem:object>
  </sem:triple>
  <sem:triple>
    <sem:subject>http://www.lds.org/vrl/specific-people/media</sem:subject>
    <sem:predicate>http://www.w3.org/2004/02/skos/core#broader</sem:predicate>
    <sem:object datatype="sem:iri">http://www.lds.org/vrl/specific-people/media/wilberg-mack</sem:object>
  </sem:triple>
  <sem:triple>
    <sem:subject>http://www.lds.org/vrl/specific-people/media</sem:subject>
    <sem:predicate>http://www.w3.org/2004/02/skos/core#broader</sem:predicate>
    <sem:object datatype="sem:iri">http://www.lds.org/vrl/specific-people/media/wilberg-rebecca</sem:object>
  </sem:triple>
  <sem:triple>
    <sem:subject>http://www.lds.org/vrl/specific-people/media</sem:subject>
    <sem:predicate>http://www.w3.org/2004/02/skos/core#broader</sem:predicate>
    <sem:object datatype="sem:iri">http://www.lds.org/vrl/specific-people/media/williams-jerry</sem:object>
  </sem:triple>
  <sem:triple>
    <sem:subject>http://www.lds.org/vrl/specific-people/media</sem:subject>
    <sem:predicate>http://www.w3.org/2004/02/skos/core#broader</sem:predicate>
    <sem:object datatype="sem:iri">http://www.lds.org/vrl/specific-people/media/willmore-leanna</sem:object>
  </sem:triple>
  <sem:triple>
    <sem:subject>http://www.lds.org/vrl/specific-people/media</sem:subject>
    <sem:predicate>http://www.w3.org/2004/02/skos/core#broader</sem:predicate>
    <sem:object datatype="sem:iri">http://www.lds.org/vrl/specific-people/media/wright-josh</sem:object>
  </sem:triple>
  <sem:triple>
    <sem:subject>http://www.lds.org/vrl/specific-people/media</sem:subject>
    <sem:predicate>http://www.w3.org/2004/02/skos/core#broader</sem:predicate>
    <sem:object datatype="sem:iri">http://www.lds.org/vrl/specific-people/media/yoo-john</sem:object>
  </sem:triple>
  <sem:triple>
    <sem:subject>http://www.lds.org/vrl/specific-people/media</sem:subject>
    <sem:predicate>http://www.w3.org/2004/02/skos/core#broader</sem:predicate>
    <sem:object datatype="sem:iri">http://www.lds.org/vrl/specific-people/media/york-michael</sem:object>
  </sem:triple>
  <sem:triple>
    <sem:subject>http://www.lds.org/vrl/specific-people/media</sem:subject>
    <sem:predicate>http://www.w3.org/2004/02/skos/core#broader</sem:predicate>
    <sem:object datatype="sem:iri">http://www.lds.org/vrl/specific-people/media/zabala-adriana</sem:object>
  </sem:triple>
</sem:triples>
