<?xml version="1.0" encoding="UTF-8"?>
<ldswebml type="image" uri="/media-library/images/seasons/fall#autumn-trees-calgary-844814" xml:lang="eng" locale="eng" status="publish" xmlns:its="http://www.w3.org/2005/11/its">
  <search-meta>
      <uri-title its:translate="no">autumn-trees-calgary-844814</uri-title>
      <source>autumn-trees-calgary-844814</source>
      <publication-type its:translate="no">image</publication-type>
      <media-type its:translate="no">image</media-type>
      <publication value="ldsorg">LDS.org</publication>
      <publication-date value="2012-10-23">2012-10-23</publication-date>
      <title/>
      <description/>
      <collections>
          <collection its:translate="no">global-search</collection>
          <collection its:translate="no">media</collection>
          <collection its:translate="no">images</collection>
      </collections>
      <subjects>
          <subject>Autumn</subject>
          <subject>Fall</subject>
          <subject>Lawns</subject>
          <subject>Leaves</subject>
          <subject>Nature</subject>
          <subject>Paths</subject>
          <subject>Pathways</subject>
          <subject>Seasons</subject>
          <subject>Trails</subject>
          <subject>Tree Trunks</subject>
          <subject>Trees</subject>
          <subject>Canada</subject>
          <subject>Calgary (Alberta)</subject>
      </subjects>
  </search-meta>
  <no-search>
      <path>http://media.ldscdn.org/images/media-library/seasons/fall/autumn-trees-calgary-844814-gallery.jpg</path>
      <images>
          <small its:translate="no">http://media.ldscdn.org/images/media-library/seasons/fall/autumn-trees-calgary-844814-thumbnail.jpg</small>
      </images>
          <download-urls>
              <download-url>
                  <label>Mobile</label>
                  <size>307 KB</size>
                  <path>http://media.ldscdn.org/images/media-library/seasons/fall/autumn-trees-calgary-844814-mobile.jpg</path>
              </download-url>
              <download-url>
                  <label>Tablet</label>
                  <size>432 KB</size>
                  <path>http://media.ldscdn.org/images/media-library/seasons/fall/autumn-trees-calgary-844814-tablet.jpg</path>
              </download-url>
              <download-url>
                  <label>Print</label>
                  <size>971 KB</size>
                  <path>http://media.ldscdn.org/images/media-library/seasons/fall/autumn-trees-calgary-844814-print.jpg</path>
              </download-url>
              <download-url>
                  <label>Wallpaper</label>
                  <size>1.5 MB</size>
                  <path>http://media.ldscdn.org/images/media-library/seasons/fall/autumn-trees-calgary-844814-wallpaper.jpg</path>
              </download-url>
          </download-urls>
  </no-search>
</ldswebml>
