<?xml version="1.0" encoding="UTF-8"?>
<ldswebml type="image" uri="/media-library/images/teachings-of-presidents-of-the-church/george-albert-smith#george-albert-smith-4-775275" xml:lang="eng" locale="eng" status="publish">
  <search-meta>
      <uri-title its:translate="no" xmlns:its="http://www.w3.org/2005/11/its">george-albert-smith-4-775275</uri-title>
      <source>george-albert-smith-4-775275</source>
      <publication-type its:translate="no" xmlns:its="http://www.w3.org/2005/11/its">image</publication-type>
      <media-type its:translate="no" xmlns:its="http://www.w3.org/2005/11/its">image</media-type>
      <publication value="ldsorg">LDS.org</publication>
      <publication-date value="2012-04-09">2012-04-09</publication-date>
      <title/>
      <description/>
      <collections>
          <collection its:translate="no" xmlns:its="http://www.w3.org/2005/11/its">global-search</collection>
          <collection its:translate="no" xmlns:its="http://www.w3.org/2005/11/its">media</collection>
          <collection its:translate="no" xmlns:its="http://www.w3.org/2005/11/its">images</collection>
      </collections>
      <subjects>
          <subject>32480</subject>
          <subject>GAS_016.eps</subject>
          <subject>GAS_016.jpg</subject>
          <subject>GAS_016alt.eps</subject>
          <subject>PD00000918</subject>
          <subject>Childhood</subject>
          <subject>LDS Church Leaders</subject>
          <subject>LDS Church Presidents</subject>
          <subject>Portraits</subject>
          <subject>Smith</subject>
          <subject>George Albert</subject>
      </subjects>
  </search-meta>
  <no-search>
      <path>http://media.ldscdn.org/images/media-library/teachings-of-presidents-of-the-church/george-albert-smith/george-albert-smith-4-775275-gallery.jpg</path>
      <images>
          <small its:translate="no" xmlns:its="http://www.w3.org/2005/11/its">http://media.ldscdn.org/images/media-library/teachings-of-presidents-of-the-church/george-albert-smith/george-albert-smith-4-775275-thumbnail.jpg</small>
      </images>
          <download-urls>
              <download-url>
                  <label>Mobile</label>
                  <size>90 KB</size>
                  <path>http://media.ldscdn.org/images/media-library/teachings-of-presidents-of-the-church/george-albert-smith/george-albert-smith-4-775275-mobile.jpg</path>
              </download-url>
              <download-url>
                  <label>Tablet</label>
                  <size>119 KB</size>
                  <path>http://media.ldscdn.org/images/media-library/teachings-of-presidents-of-the-church/george-albert-smith/george-albert-smith-4-775275-tablet.jpg</path>
              </download-url>
          </download-urls>
  </no-search>
<ldse-meta its:translate="no" xmlns="http://lds.org/code/lds-edit" xmlns:its="http://www.w3.org/2005/11/its"><document id="george-albert-smith-4-775275" locale="eng" uri="/media-library/images/teachings-of-presidents-of-the-church/george-albert-smith#george-albert-smith-4-775275" status="publish" site="ldsorg" source="chq" words="141" tgp="0.493"/><created username="lds-edit" userid=""/><last-modified date="2012-05-10T12:26:12.550235-06:00" username="lds-edit" userid=""/></ldse-meta></ldswebml>
