<?xml version="1.0" encoding="UTF-8"?>
<sem:triples xmlns:sem="http://marklogic.com/semantics">
  <sem:triple>
    <sem:subject>http://www.lds.org/concept/gs/rainbow</sem:subject>
    <sem:predicate>http://www.w3.org/1999/02/22-rdf-syntax-ns#type</sem:predicate>
    <sem:object datatype="sem:iri">http://www.w3.org/2004/02/skos/core#Concept</sem:object>
  </sem:triple>
  <sem:triple>
    <sem:subject>http://www.lds.org/concept/gs/rainbow</sem:subject>
    <sem:predicate>http://www.w3.org/2004/02/skos/core#prefLabel</sem:predicate>
    <sem:object xml:lang="eng" datatype="xsd:string">Rainbow</sem:object>
  </sem:triple>
  <sem:triple>
    <sem:subject>http://www.lds.org/concept/gs/rainbow</sem:subject>
    <sem:predicate>http://www.lds.org/core#entityType</sem:predicate>
    <sem:object datatype="sem:iri">http://www.lds.org/Topic</sem:object>
  </sem:triple>
  <sem:triple>
    <sem:subject>http://www.lds.org/concept/gs/rainbow</sem:subject>
    <sem:predicate>http://www.lds.org/core#partOfSpeech</sem:predicate>
    <sem:object xml:lang="eng" datatype="xsd:string">noun</sem:object>
  </sem:triple>
  <sem:triple>
    <sem:subject>http://www.lds.org/concept/gs/rainbow</sem:subject>
    <sem:predicate>http://www.lds.org/core#instanceOf</sem:predicate>
    <sem:object datatype="xsd:anyURI">http://www.lds.org/scriptures/gs/rainbow</sem:object>
  </sem:triple>
  <sem:triple>
    <sem:subject>http://www.lds.org/concept/gs/rainbow</sem:subject>
    <sem:predicate>http://www.w3.org/2004/02/skos/core#definition</sem:predicate>
    <sem:object xml:lang="eng" datatype="xsd:string">The sign or token of God’s covenant with Noah ().  explains that the covenant includes the promises that the earth will never again be covered with a flood of water, that the Zion of Enoch will return, and that the Lord will come again to dwell on the earth.</sem:object>
  </sem:triple>
  <sem:triple>
    <sem:subject>http://www.lds.org/concept/gs/rainbow</sem:subject>
    <sem:predicate>http://www.lds.org/core#instanceOf</sem:predicate>
    <sem:object datatype="xsd:anyURI">http://www.lds.org/scriptures/tg/rainbow?lang=eng</sem:object>
  </sem:triple>
  <sem:triple>
    <sem:subject>http://www.lds.org/concept/gs/rainbow</sem:subject>
    <sem:predicate>http://www.lds.org/core#instanceOf</sem:predicate>
    <sem:object datatype="xsd:anyURI">http://www.lds.org/scriptures/bd/rainbow?lang=eng</sem:object>
  </sem:triple>
  <sem:triple>
    <sem:subject>http://www.lds.org/concept/gs/rainbow</sem:subject>
    <sem:predicate>http://www.w3.org/2004/02/skos/core#related</sem:predicate>
    <sem:object datatype="sem:iri">http://www.lds.org/concept/gs/ark</sem:object>
  </sem:triple>
  <sem:triple>
    <sem:subject>http://www.lds.org/concept/gs/rainbow</sem:subject>
    <sem:predicate>http://www.w3.org/2004/02/skos/core#related</sem:predicate>
    <sem:object datatype="sem:iri">http://www.lds.org/concept/gs/flood-at-noahs-time</sem:object>
  </sem:triple>
  <sem:triple>
    <sem:subject>http://www.lds.org/concept/gs/rainbow</sem:subject>
    <sem:predicate>http://www.w3.org/2004/02/skos/core#related</sem:predicate>
    <sem:object datatype="sem:iri">http://www.lds.org/concept/gs/noah-1</sem:object>
  </sem:triple>
  <sem:triple>
    <sem:subject>http://www.lds.org/concept/gs/rainbow</sem:subject>
    <sem:predicate>http://www.w3.org/2004/02/skos/core#inScheme</sem:predicate>
    <sem:object datatype="sem:iri">http://www.lds.org/concept-scheme/guide-to-the-scriptures</sem:object>
  </sem:triple>
  <sem:triple>
    <sem:subject>http://www.lds.org/concept/gs/rainbow</sem:subject>
    <sem:predicate>http://www.lds.org/core#relCount</sem:predicate>
    <sem:object datatype="xsd:integer">3</sem:object>
  </sem:triple>
</sem:triples>
